{
    "tMBdem-e9Fk": [
        360,
        360
    ],
    "X7NlnFZXsy8": [
        1920,
        1080
    ],
    "4-e2bCkzkIs": [
        1920,
        1080
    ],
    "GJQDpFbK3fU": [
        1280,
        720
    ],
    "uTxW7o9c5MI": [
        810,
        480
    ],
    "4ZPQuHMhniQ": [
        1920,
        1080
    ],
    "1rYs_wUZ0hM": [
        1920,
        1080
    ],
    "yNt0yY3JbIM": [
        1920,
        1080
    ],
    "1cNv7eqjR3Q": [
        1280,
        720
    ],
    "DrG08jVhbLw": [
        1280,
        720
    ],
    "0rtGwRFG0Hk": [
        1920,
        1080
    ],
    "RGsKOHu4D8o": [
        1280,
        720
    ],
    "9s3k6j3ft0w": [
        1280,
        720
    ],
    "Z6AwsPKbHAU": [
        1920,
        1080
    ],
    "qyL_cYxV6QA": [
        1920,
        1080
    ],
    "3LasetIg7Q8": [
        640,
        480
    ],
    "TJP34JxI9DQ": [
        1280,
        720
    ],
    "2-XJcrvRCXM": [
        640,
        480
    ],
    "-5m_16X3IMo": [
        854,
        480
    ],
    "5v8QkijeqHk": [
        1920,
        1080
    ],
    "1ugesWXaSmQ": [
        1920,
        1080
    ],
    "-89_obTUlSU": [
        1280,
        720
    ],
    "42dbuhteL4o": [
        1920,
        1080
    ],
    "0tcT84VeD2c": [
        1280,
        720
    ],
    "AJ9lahVmWIw": [
        1280,
        720
    ],
    "UDhi7Y2ahPw": [
        1920,
        1080
    ],
    "Vuy2nrJz0Zw": [
        1920,
        1080
    ],
    "0vH1TYaf6v4": [
        1280,
        720
    ],
    "vce5Qu6Ur1g": [
        1920,
        1080
    ],
    "-q5MfvBP9RE": [
        854,
        476
    ],
    "1EXUX0MB_68": [
        1280,
        720
    ],
    "VrJT_QXIxWA": [
        1280,
        720
    ],
    "0tkyF9Cjhk4": [
        1920,
        1080
    ],
    "0TjrAQPfJ0o": [
        1920,
        1080
    ],
    "7R4Py5WkpDo": [
        1920,
        1080
    ],
    "0MuKqqOOrxw": [
        1920,
        1080
    ],
    "ZVwEGu6vfPk": [
        1920,
        1080
    ],
    "zrxNMHHgz0g": [
        1920,
        1080
    ],
    "gSlmIS1dZpo": [
        1920,
        1080
    ],
    "yEf5Vhm_5Q4": [
        1280,
        720
    ],
    "zk4dz9-Ubsk": [
        1280,
        720
    ],
    "0p9c5Rb8XDU": [
        1920,
        1080
    ],
    "z0VEfCUQ8Hs": [
        1280,
        720
    ],
    "7ErYT9ZtHJY": [
        1920,
        1080
    ],
    "04sDcaLeEjE": [
        640,
        480
    ],
    "B6pj1jfbtMw": [
        1920,
        1080
    ],
    "-8Jnwe0lADI": [
        1920,
        1080
    ],
    "8HeJC2coREo": [
        480,
        360
    ],
    "8WAElNjtkmI": [
        1280,
        720
    ],
    "z4Y4S-7VDAo": [
        1920,
        1080
    ],
    "ZKWaGNECyEQ": [
        854,
        480
    ],
    "3tdXdU2kBOE": [
        854,
        480
    ],
    "7vW4jy2JAZI": [
        1920,
        1080
    ],
    "aDhsWnCi6bs": [
        1920,
        1080
    ],
    "7BgTWjVKoxI": [
        854,
        478
    ],
    "14RqrKRybKM": [
        1920,
        1080
    ],
    "xGTxlQ7TojE": [
        1920,
        1080
    ],
    "55RIIi1sLfM": [
        1920,
        1080
    ],
    "0Nr-YHxL72M": [
        1280,
        720
    ],
    "ys0zQlQcmWA": [
        1920,
        1080
    ],
    "hRq269sj3Dk": [
        1280,
        720
    ],
    "7TGfw_KjTn8": [
        1280,
        720
    ],
    "-2TGG1WFF3A": [
        854,
        480
    ],
    "zWsgkrYDioI": [
        1920,
        1080
    ],
    "1F94eQTx6Vo": [
        1280,
        720
    ],
    "3xLkz4f4dX0": [
        1920,
        1080
    ],
    "PzLb9Pc6q1o": [
        480,
        360
    ],
    "dOOl-Ff2H2E": [
        320,
        240
    ],
    "ZNEzk21_HwY": [
        1920,
        1080
    ],
    "pPYHEnnN08s": [
        1280,
        720
    ],
    "hFB086bopJw": [
        1920,
        1080
    ],
    "G-O-gd1HATc": [
        1280,
        720
    ],
    "0oHKJRw5jFM": [
        1920,
        1080
    ],
    "-4oyhgzPmCw": [
        640,
        344
    ],
    "4LtF8vuXd0o": [
        1280,
        720
    ],
    "YBF8gcUuPYU": [
        1920,
        1080
    ],
    "y-Wr401Bio4": [
        810,
        480
    ],
    "4Bn77GTJ63c": [
        1920,
        1080
    ],
    "8TIweTobAZQ": [
        1280,
        720
    ],
    "Q4XwTDpUB3o": [
        854,
        480
    ],
    "B1jLazyO3yQ": [
        1920,
        1080
    ],
    "V7IQSlDMf3U": [
        854,
        480
    ],
    "X4F06nMR664": [
        1280,
        720
    ],
    "5R_4ev_1J9E": [
        1920,
        1080
    ],
    "GEn8L3VODk8": [
        1920,
        1080
    ],
    "CM4iLdepaqU": [
        256,
        144
    ],
    "096nESIA2e8": [
        1920,
        1080
    ],
    "48v-DHaGfcg": [
        640,
        360
    ],
    "ZY2mpcrvljw": [
        1920,
        1080
    ],
    "YTXDUNGlJyQ": [
        1280,
        720
    ],
    "aRDICA9x9vg": [
        1280,
        720
    ],
    "oksqDooy6Ls": [
        1920,
        1080
    ],
    "WDWEsTCY5_k": [
        1920,
        1080
    ],
    "45wbPSTfLBo": [
        1920,
        1080
    ],
    "yS4ccYx8UAU": [
        1280,
        720
    ],
    "tFsLL2xvpdQ": [
        1920,
        1080
    ],
    "z_WPV8ipFh8": [
        1280,
        720
    ],
    "2kop4occwec": [
        1920,
        1080
    ],
    "2EoaCR2thUs": [
        1920,
        1080
    ],
    "Vxjhzu7l57E": [
        426,
        240
    ],
    "1iV43wsHXS0": [
        352,
        262
    ],
    "y-QHF7dDiNI": [
        640,
        480
    ],
    "Z1wjhJaAC4Y": [
        1280,
        720
    ],
    "1S6S2XxZCEI": [
        854,
        480
    ],
    "1CfeeRIdvgc": [
        1280,
        720
    ],
    "4hMJTKh3yFQ": [
        1920,
        1080
    ],
    "qsXwvn-3zl8": [
        1280,
        720
    ],
    "b9j1xqlnOMU": [
        1280,
        720
    ],
    "2cnkxMe8b4Y": [
        1920,
        1080
    ],
    "x3zxme5vxgU": [
        1920,
        1080
    ],
    "GrIXOsIM1C4": [
        1280,
        720
    ],
    "1fsBD8kD1Gw": [
        960,
        720
    ],
    "_9mgOkzm-xg": [
        1280,
        720
    ],
    "2--rBUf69DM": [
        1280,
        720
    ],
    "9UPRirN6Os0": [
        1280,
        720
    ],
    "4UnrxxBkN-Y": [
        640,
        480
    ],
    "FLB0LqX3E7Q": [
        1280,
        720
    ],
    "UO9ERP8Gvr8": [
        320,
        240
    ],
    "65ifzkFi614": [
        480,
        360
    ],
    "1EO9Qx9VD0E": [
        712,
        480
    ],
    "1eye6M0yyrs": [
        1280,
        720
    ],
    "4fRvyVg7tO8": [
        1920,
        1080
    ],
    "5XyTfM2y3hM": [
        1920,
        1080
    ],
    "zTnwgP39eAg": [
        1920,
        1080
    ],
    "faqnfPwg9R4": [
        1920,
        1080
    ],
    "lZ0zN7BiQl8": [
        1920,
        1080
    ],
    "_8BJZetE9rg": [
        480,
        360
    ],
    "CBQ9ynRIiE4": [
        1280,
        720
    ],
    "PnjCaEZpn8o": [
        426,
        240
    ],
    "AIr_S7vZOqc": [
        1280,
        720
    ],
    "znotAzoftpM": [
        1920,
        1080
    ],
    "3EaGd8JQWtI": [
        1920,
        1080
    ],
    "4V956PuOWcU": [
        1920,
        1080
    ],
    "j9qQg_KbX5A": [
        1920,
        1080
    ],
    "F-B_hPCTtQo": [
        1920,
        1080
    ],
    "zl-CWjwhwNQ": [
        1280,
        720
    ],
    "fug8EZr25yA": [
        854,
        480
    ],
    "0xzMkL5FGlE": [
        640,
        480
    ],
    "4bejyXi0Gs0": [
        480,
        360
    ],
    "4u_fiTlBpLU": [
        1280,
        720
    ],
    "zV72T3vzAi4": [
        1920,
        1080
    ],
    "WSXGBL_KGdQ": [
        1920,
        1080
    ],
    "2mQNNFaAvc4": [
        320,
        240
    ],
    "_3zVcyfIheo": [
        1280,
        720
    ],
    "VMh-gPt6Rwk": [
        1280,
        720
    ],
    "_47FQRlGy9w": [
        480,
        360
    ],
    "ggILameZ7P4": [
        1280,
        720
    ],
    "BUz8xzQ5EwQ": [
        640,
        360
    ],
    "ecVZ791EQ5E": [
        1920,
        1080
    ],
    "fIfoazNdrCY": [
        1920,
        1080
    ],
    "7X7gH_1FpOk": [
        1280,
        720
    ],
    "0ypSLkV3tac": [
        1280,
        720
    ],
    "0hjj7X9hdjY": [
        1280,
        720
    ],
    "85kcRoln4ZE": [
        640,
        360
    ],
    "YvDmYSXs7gU": [
        1280,
        720
    ],
    "uhLqVM-j-8E": [
        1920,
        1080
    ],
    "xG9G-qHNbtY": [
        480,
        360
    ],
    "ZUYyg4iLYQw": [
        1920,
        1080
    ],
    "yTIIG-sz0ig": [
        1920,
        1080
    ],
    "ntVTeJiepLY": [
        640,
        480
    ],
    "a2j_3CLvhXE": [
        1280,
        720
    ],
    "0VbRh9Ug6Xw": [
        1280,
        720
    ],
    "1KNr2qzTMbQ": [
        1280,
        720
    ],
    "zuYFVFvCRMs": [
        1280,
        720
    ],
    "vSM7AqEOyxg": [
        1920,
        1080
    ],
    "0OeJWR71g90": [
        1920,
        1080
    ],
    "1Q1_jE4IIls": [
        1280,
        720
    ],
    "ZMHx-GmKnIo": [
        480,
        360
    ],
    "yZVJ0RbSTMo": [
        1280,
        720
    ],
    "uWaWeVmpYvQ": [
        1280,
        720
    ],
    "2y_Fm1U2RZg": [
        1280,
        720
    ],
    "ojVZi1ffUAE": [
        1920,
        1080
    ],
    "r1ZvuOz3EFM": [
        1920,
        1080
    ],
    "Gf4eEhDpxgk": [
        480,
        360
    ],
    "_7RI2fa78aE": [
        1440,
        1080
    ],
    "0WEHonjY4KU": [
        1920,
        1080
    ],
    "-_9E7vmxi4o": [
        1280,
        720
    ],
    "4pJFyDcA4Zg": [
        1920,
        1080
    ],
    "zsOHzVjwfF4": [
        1920,
        1080
    ],
    "14DhNyWddXg": [
        1280,
        720
    ],
    "yKirllGoYck": [
        1920,
        1080
    ],
    "2fCWfPYtdio": [
        1280,
        720
    ],
    "ZhS1SGJAHBw": [
        640,
        352
    ],
    "zqgm2QTNSYU": [
        640,
        360
    ],
    "5smvD4mkIv8": [
        1280,
        720
    ],
    "PAXT4fJap6c": [
        1920,
        1080
    ],
    "0GR1C_CAywU": [
        1920,
        1080
    ],
    "6xpIetPLamE": [
        480,
        360
    ],
    "h-3F9WUQcMk": [
        1920,
        1080
    ],
    "2fjQl7lptAM": [
        640,
        480
    ],
    "zUQGW3bpWOY": [
        640,
        360
    ],
    "5xDmFmoPJgk": [
        1280,
        720
    ],
    "64i4AvZ8mPc": [
        1920,
        1080
    ],
    "tC4swUMV17c": [
        1280,
        720
    ],
    "2Cen74-SM44": [
        1920,
        1080
    ],
    "0nQqtpRpiRo": [
        1280,
        720
    ],
    "zglsDdaBf4g": [
        1920,
        1080
    ],
    "99RvUNcJyYY": [
        1280,
        720
    ],
    "aG_NHgTeWmA": [
        1280,
        720
    ],
    "zPkgeKTO2YM": [
        1280,
        720
    ],
    "7_78Wq7wUsg": [
        720,
        480
    ],
    "7jrq6iRYc2s": [
        1920,
        1080
    ],
    "7mabCfrc90Y": [
        360,
        480
    ],
    "Q3fI43q-sj8": [
        640,
        360
    ],
    "YDSJTx8xJ4E": [
        1440,
        1080
    ],
    "ssKGdBQ3xoo": [
        480,
        360
    ],
    "Ztk-1ssNgUo": [
        1920,
        1080
    ],
    "fLMkcTrdDMM": [
        1920,
        1080
    ],
    "01FLJjr-vJM": [
        1280,
        720
    ],
    "1asUmD71FKs": [
        854,
        480
    ],
    "0lfxYLc06hA": [
        1280,
        720
    ],
    "9eyNx_vWqiQ": [
        640,
        480
    ],
    "X8KPsREQUQc": [
        1920,
        1080
    ],
    "U_2di96G9JM": [
        1920,
        1080
    ],
    "-1okAudsnAc": [
        1920,
        1080
    ],
    "zUQDSh-aT00": [
        1920,
        1080
    ],
    "1i0Demm-T-o": [
        480,
        360
    ],
    "74Pyl6MzS_c": [
        1920,
        1080
    ],
    "9G7ibHbDC1c": [
        1920,
        1080
    ],
    "zO7LIiIMVgk": [
        1920,
        1080
    ],
    "zqDmjo0wAsw": [
        1920,
        1080
    ],
    "WmdhvNibZrY": [
        1920,
        1080
    ],
    "3PJTVE554D8": [
        1920,
        1080
    ],
    "V8jguJ6g1vE": [
        1280,
        720
    ],
    "VjkFOVbxsow": [
        1280,
        720
    ],
    "0GGOV4f7mKQ": [
        810,
        480
    ],
    "3MTpNZf8seM": [
        640,
        360
    ],
    "vHFkJPsnMkI": [
        320,
        240
    ],
    "FqpUe4vcKT8": [
        644,
        480
    ],
    "fngz89219mg": [
        1280,
        720
    ],
    "NpHHzTFjfYY": [
        640,
        480
    ],
    "_hBarzzLX9Y": [
        1280,
        720
    ],
    "tgf-zfEkQA8": [
        654,
        480
    ],
    "2cZUZBdw0cA": [
        1920,
        1080
    ],
    "zfAksNHc3RQ": [
        1280,
        720
    ],
    "WeQ9Msq8iAs": [
        1920,
        1080
    ],
    "93a3JdSH7r8": [
        1280,
        720
    ],
    "1p9jOT2Zgkg": [
        480,
        360
    ],
    "vHRl4oW3T-E": [
        1280,
        720
    ],
    "3xFZjlM1sbQ": [
        640,
        480
    ],
    "F1K85WqQpiI": [
        640,
        480
    ],
    "ZEDu5fomB_0": [
        1920,
        1080
    ],
    "f5D_OqA3pQU": [
        640,
        360
    ],
    "f8amTESTBKY": [
        1920,
        1080
    ],
    "zS2-eyhlRA4": [
        640,
        480
    ],
    "OHxPexp2XiU": [
        1920,
        1080
    ],
    "ZT4jDBsnHJ4": [
        1920,
        1080
    ],
    "YGlK-hY1dr4": [
        1920,
        1080
    ],
    "0IYV4JZwGT4": [
        1920,
        1080
    ],
    "0uG0TwmuLHg": [
        640,
        480
    ]
}